gptintegration/__init__.py
gptintegration/gpt_integration.py
GPTIntegration-0.0.7.dist-info/LICENSE
GPTIntegration-0.0.7.dist-info/METADATA
GPTIntegration-0.0.7.dist-info/WHEEL
GPTIntegration-0.0.7.dist-info/top_level.txt
GPTIntegration-0.0.7.dist-info/RECORD
