Metadata-Version: 2.1
Name: GPTIntegration
Version: 0.0.7
Summary: A module for integrating various GPT models for diverse tasks.
Home-page: https://github.com/chigwell/GPTIntegration
Author: Eugene Evstafev
Author-email: chigwel@gmail.com
License: UNKNOWN
Platform: UNKNOWN
Classifier: Programming Language :: Python :: 3
Classifier: License :: OSI Approved :: MIT License
Classifier: Operating System :: OS Independent
Requires-Python: >=3.6
Requires-Dist: openai
